odoo8_addon_web_dashboard_tile-8.0.4.0.0-py2.7-nspkg.pth
odoo_addons/web_dashboard_tile/__openerp__.py
odoo_addons/web_dashboard_tile/__init__.py
odoo_addons/web_dashboard_tile/README.rst
odoo_addons/web_dashboard_tile/security/ir.model.access.csv
odoo_addons/web_dashboard_tile/security/rules.xml
odoo_addons/web_dashboard_tile/migrations/8.0.4.0/post-migration.py
odoo_addons/web_dashboard_tile/migrations/8.0.3.0/post-migration.py
odoo_addons/web_dashboard_tile/models/tile_tile.py
odoo_addons/web_dashboard_tile/models/__init__.py
odoo_addons/web_dashboard_tile/i18n/pt.po
odoo_addons/web_dashboard_tile/i18n/it.po
odoo_addons/web_dashboard_tile/i18n/es.po
odoo_addons/web_dashboard_tile/i18n/ar.po
odoo_addons/web_dashboard_tile/i18n/tr.po
odoo_addons/web_dashboard_tile/i18n/hr.po
odoo_addons/web_dashboard_tile/i18n/gl.po
odoo_addons/web_dashboard_tile/i18n/web_dashboard_tile.pot
odoo_addons/web_dashboard_tile/i18n/ca.po
odoo_addons/web_dashboard_tile/i18n/sl.po
odoo_addons/web_dashboard_tile/i18n/es_ES.po
odoo_addons/web_dashboard_tile/i18n/pt_PT.po
odoo_addons/web_dashboard_tile/i18n/nl.po
odoo_addons/web_dashboard_tile/i18n/am.po
odoo_addons/web_dashboard_tile/i18n/de.po
odoo_addons/web_dashboard_tile/i18n/fr.po
odoo_addons/web_dashboard_tile/i18n/pt_BR.po
odoo_addons/web_dashboard_tile/i18n/el_GR.po
odoo_addons/web_dashboard_tile/i18n/fi.po
odoo_addons/web_dashboard_tile/views/tile.xml
odoo_addons/web_dashboard_tile/views/templates.xml
odoo_addons/web_dashboard_tile/tests/__init__.py
odoo_addons/web_dashboard_tile/tests/test_tile.py
odoo_addons/web_dashboard_tile/demo/tile_tile.yml
odoo_addons/web_dashboard_tile/demo/res_groups.yml
odoo_addons/web_dashboard_tile/static/description/icon.png
odoo_addons/web_dashboard_tile/static/src/img/median.png
odoo_addons/web_dashboard_tile/static/src/img/screenshot_dashboard.png
odoo_addons/web_dashboard_tile/static/src/img/screenshot_action_click.png
odoo8_addon_web_dashboard_tile-8.0.4.0.0.dist-info/top_level.txt
odoo8_addon_web_dashboard_tile-8.0.4.0.0.dist-info/WHEEL
odoo8_addon_web_dashboard_tile-8.0.4.0.0.dist-info/RECORD
odoo8_addon_web_dashboard_tile-8.0.4.0.0.dist-info/metadata.json
odoo8_addon_web_dashboard_tile-8.0.4.0.0.dist-info/DESCRIPTION.rst
odoo8_addon_web_dashboard_tile-8.0.4.0.0.dist-info/METADATA
odoo8_addon_web_dashboard_tile-8.0.4.0.0.dist-info/namespace_packages.txt
