Metadata-Version: 2.0
Name: odoo8-addon-web-dashboard-tile
Version: 8.0.4.0.0
Summary: Add Tiles to Dashboard
Home-page: UNKNOWN
Author: initOS GmbH & Co. KG, GRAP, Odoo Community Association (OCA)
Author-email: support@odoo-community.org
License: AGPL-3
Platform: UNKNOWN
Requires-Dist: odoo (<9.0a,>=8.0a)
Requires-Dist: odoo8-addon-web-widget-color
Classifier: Programming Language :: Python :: 2.7
Classifier: Framework :: Odoo
Classifier: License :: OSI Approved :: GNU Affero General Public License v3
